<?xml version="1.0" encoding="UTF-8"?>
<databaseChangeLog xmlns="http://www.liquibase.org/xml/ns/dbchangelog"
                   xmlns:ext="http://www.liquibase.org/xml/ns/dbchangelog-ext"
                   xmlns:pro="http://www.liquibase.org/xml/ns/pro"
                   xmlns:xsi="http://www.w3.org/2001/XMLSchema-instance"
                   xsi:schemaLocation="http://www.liquibase.org/xml/ns/dbchangelog-ext
                   http://www.liquibase.org/xml/ns/dbchangelog/dbchangelog-ext.xsd
                   http://www.liquibase.org/xml/ns/pro
                   http://www.liquibase.org/xml/ns/pro/liquibase-pro-3.10.xsd
                   http://www.liquibase.org/xml/ns/dbchangelog
                   http://www.liquibase.org/xml/ns/dbchangelog/dbchangelog-3.10.xsd">

    <changeSet author="admin" id="11">
        <preConditions onFail="MARK_RAN">
            <not>
                <foreignKeyConstraintExists foreignKeyName="ORDER_fkey"/>
            </not>
        </preConditions>
        <addForeignKeyConstraint baseColumnNames="order_id" baseTableName="PAYMENT" constraintName="ORDER_fkey" deferrable="false" initiallyDeferred="false" onDelete="NO ACTION" onUpdate="NO ACTION" referencedColumnNames="id" referencedTableName="ORDER"/>
<!--        <addForeignKeyConstraint baseColumnNames="order_id" baseTableName="PAYMENT" constraintName="ORDER_fkey" deferrable="false" initiallyDeferred="false" onDelete="NO ACTION" onUpdate="NO ACTION" referencedColumnNames="id" referencedTableName="ORDER" validate="true"/>-->
        <rollback>
            <dropForeignKeyConstraint baseTableName="PAYMENT" constraintName="ORDER_fkey"/>
        </rollback>
    </changeSet>

</databaseChangeLog>